wz_code/__init__.py
wz_code/_build/__init__.py
wz_code/_build/generator.py
wz_code/_speedups/__init__.py
wz_code/_speedups/search.pyx
wz_code/_speedups/similarity.pyx
wz_code/_speedups/trie.pyx
wz_code/cli.py
wz_code/core.py
wz_code/data/__init__.py
wz_code/data/correspondences.py
wz_code/data/wz2008.py
wz_code/data/wz2025.py
wz_code/exceptions.py
wz_code/models.py
wz_code/utils.py
wz_code-0.1.0.dist-info/LICENSE
wz_code-0.1.0.dist-info/METADATA
wz_code-0.1.0.dist-info/WHEEL
wz_code-0.1.0.dist-info/entry_points.txt
wz_code-0.1.0.dist-info/RECORD
