Metadata-Version: 2.3
Name: wz-code
Version: 0.1.0
Summary: High-performance German economic classification (WZ) library
License: MIT
Keywords: wz,classification,german,wirtschaftszweig,economic,statistics
Author: Paul Porstendorfer
Author-email: paul.porstendorfer@bandbyte.com
Requires-Python: >=3.8
Classifier: Development Status :: 3 - Alpha
Classifier: Intended Audience :: Developers
Classifier: Intended Audience :: Science/Research
Classifier: License :: OSI Approved :: MIT License
Classifier: Programming Language :: Python :: 3
Classifier: Programming Language :: Python :: 3.8
Classifier: Programming Language :: Python :: 3.9
Classifier: Programming Language :: Python :: 3.10
Classifier: Programming Language :: Python :: 3.11
Classifier: Programming Language :: Python :: 3.12
Classifier: Topic :: Office/Business
Classifier: Topic :: Scientific/Engineering
Provides-Extra: dev
Provides-Extra: speedups
Requires-Dist: black (>=23.0.0) ; extra == "dev"
Requires-Dist: cython (>=3.0.0) ; extra == "speedups"
Requires-Dist: mypy (>=1.0.0) ; extra == "dev"
Requires-Dist: pytest (>=7.0.0) ; extra == "dev"
Requires-Dist: pytest-cov (>=4.0.0) ; extra == "dev"
Requires-Dist: ruff (>=0.1.0) ; extra == "dev"
Project-URL: Documentation, https://github.com/bandbyte/wz-code#readme
Project-URL: Homepage, https://github.com/bandbyte/wz-code
Project-URL: Issues, https://github.com/bandbyte/wz-code/issues
Project-URL: Repository, https://github.com/bandbyte/wz-code
